ovos_tts_plugin_silero/__init__.py
ovos_tts_plugin_silero/tts.py
ovos_tts_plugin_silero/version.py
ovos_tts_plugin_silero-0.3.1.dist-info/LICENSE
ovos_tts_plugin_silero-0.3.1.dist-info/METADATA
ovos_tts_plugin_silero-0.3.1.dist-info/WHEEL
ovos_tts_plugin_silero-0.3.1.dist-info/entry_points.txt
ovos_tts_plugin_silero-0.3.1.dist-info/top_level.txt
ovos_tts_plugin_silero-0.3.1.dist-info/zip-safe
ovos_tts_plugin_silero-0.3.1.dist-info/RECORD
